yandextank/__init__.py
yandextank/version.py
yandextank/aggregator/__init__.py
yandextank/aggregator/aggregator.py
yandextank/aggregator/chopper.py
yandextank/aggregator/tank_aggregator.py
yandextank/aggregator/config/phout.json
yandextank/ammo_validator/__init__.py
yandextank/ammo_validator/common.py
yandextank/ammo_validator/validator.py
yandextank/ammo_validator/validators/__init__.py
yandextank/ammo_validator/validators/json_grpc.py
yandextank/ammo_validator/validators/json_http.py
yandextank/ammo_validator/validators/phantom.py
yandextank/ammo_validator/validators/uri.py
yandextank/ammo_validator/validators/uri_inline.py
yandextank/ammo_validator/validators/uripost.py
yandextank/common/__init__.py
yandextank/common/const.py
yandextank/common/exceptions.py
yandextank/common/interfaces.py
yandextank/common/monitoring.py
yandextank/common/util.py
yandextank/common/tests/__init__.py
yandextank/common/tests/test_interfaces.py
yandextank/common/tests/test_monitoring.py
yandextank/common/tests/test_util.py
yandextank/config_converter/__init__.py
yandextank/config_converter/converter.py
yandextank/contrib/__init__.py
yandextank/contrib/netort/__init__.py
yandextank/contrib/netort/netort/__init__.py
yandextank/contrib/netort/netort/cli.py
yandextank/contrib/netort/netort/data_processing.py
yandextank/contrib/netort/netort/logging_and_signals.py
yandextank/contrib/netort/netort/process.py
yandextank/contrib/netort/netort/resource.py
yandextank/contrib/netort/netort/validated_config.py
yandextank/contrib/netort/netort/data_manager/__init__.py
yandextank/contrib/netort/netort/data_manager/manager.py
yandextank/contrib/netort/netort/data_manager/router.py
yandextank/contrib/netort/netort/data_manager/clients/__init__.py
yandextank/contrib/netort/netort/data_manager/clients/local.py
yandextank/contrib/netort/netort/data_manager/clients/luna.py
yandextank/contrib/netort/netort/data_manager/clients/lunapark_volta.py
yandextank-2.0.12.dist-info/AUTHORS.md
yandextank-2.0.12.dist-info/LICENSE.md
yandextank-2.0.12.dist-info/METADATA
yandextank-2.0.12.dist-info/WHEEL
yandextank-2.0.12.dist-info/entry_points.txt
yandextank-2.0.12.dist-info/top_level.txt
yandextank-2.0.12.dist-info/RECORD
