Metadata-Version: 2.1
Name: yandextank
Version: 2.0.12
Summary: a performance measurement tool
Home-page: http://yandex.github.io/yandex-tank/
Maintainer: Yandex Load Team
Maintainer-email: load@yandex-team.ru
License: LGPLv2
Classifier: Development Status :: 5 - Production/Stable
Classifier: Environment :: Console
Classifier: Environment :: Web Environment
Classifier: Intended Audience :: End Users/Desktop
Classifier: Intended Audience :: Developers
Classifier: Intended Audience :: System Administrators
Classifier: License :: OSI Approved :: GNU Lesser General Public License v2 or later (LGPLv2+)
Classifier: Operating System :: POSIX
Classifier: Topic :: Software Development :: Quality Assurance
Classifier: Topic :: Software Development :: Testing
Classifier: Topic :: Software Development :: Testing :: Traffic Generation
Classifier: Programming Language :: Python :: 3.8
Requires-Python: >=3.12
License-File: LICENSE.md
License-File: AUTHORS.md
Requires-Dist: psutil>=5.9.8
Requires-Dist: requests>=2.31.0
Requires-Dist: pandas<=2.0.3
Requires-Dist: numpy<=1.26.4
Requires-Dist: pip>=24.0
Requires-Dist: pyyaml>=5.4
Requires-Dist: cerberus>=1.3.5
Requires-Dist: influxdb>=5.3.1
Requires-Dist: retrying>=1.3.4
Requires-Dist: pytest-runner
Requires-Dist: pyserial
Requires-Dist: retrying
Requires-Dist: six>=1.16.0
Requires-Dist: environ-config>=23.2.0
